boobs/__init__.py
boobs/api/__init__.py
boobs/api/abc.py
boobs/api/api.py
boobs/api/utils/__init__.py
boobs/api/utils/file_util.py
boobs/api/utils/token_util.py
boobs/api/validators/__init__.py
boobs/api/validators/abc.py
boobs/api/validators/request.py
boobs/api/validators/response.py
boobs/bot/__init__.py
boobs/bot/abc.py
boobs/bot/blueprint/__init__.py
boobs/bot/blueprint/abc.py
boobs/bot/blueprint/default.py
boobs/bot/bot.py
boobs/bot/dispatch/__init__.py
boobs/bot/dispatch/dispatcher/__init__.py
boobs/bot/dispatch/dispatcher/abc.py
boobs/bot/dispatch/dispatcher/default.py
boobs/bot/dispatch/handler/__init__.py
boobs/bot/dispatch/handler/abc.py
boobs/bot/dispatch/handler/func.py
boobs/bot/dispatch/middlewares/__init__.py
boobs/bot/dispatch/middlewares/abc.py
boobs/bot/dispatch/router/__init__.py
boobs/bot/dispatch/router/abc.py
boobs/bot/dispatch/router/default.py
boobs/bot/dispatch/view/__init__.py
boobs/bot/dispatch/view/abc.py
boobs/bot/dispatch/view/impl.py
boobs/bot/polling/__init__.py
boobs/bot/polling/abc.py
boobs/bot/polling/default.py
boobs/bot/rules/__init__.py
boobs/bot/rules/abc.py
boobs/bot/rules/base.py
boobs/bot/rules/message.py
boobs/bot/states/__init__.py
boobs/bot/states/dispenser/__init__.py
boobs/bot/states/dispenser/abc.py
boobs/bot/states/dispenser/default.py
boobs/bot/states/types.py
boobs/bot/updates/__init__.py
boobs/bot/updates/base.py
boobs/bot/updates/types.py
boobs/contrib/__init__.py
boobs/contrib/middleware/__init__.py
boobs/contrib/rules/__init__.py
boobs/contrib/storage/__init__.py
boobs/contrib/storage/redis.py
boobs/errors/__init__.py
boobs/errors/base_exceptions.py
boobs/errors/code_exception.py
boobs/errors/error_handler/__init__.py
boobs/errors/error_handler/abc.py
boobs/errors/error_handler/error_handler.py
boobs/modules.py
boobs/net/__init__.py
boobs/net/abc.py
boobs/net/default.py
boobs/tools/__init__.py
boobs/tools/delayed_task.py
boobs/tools/keyboard/__init__.py
boobs/tools/keyboard/abc.py
boobs-0.6.9.dist-info/LICENSE
boobs-0.6.9.dist-info/METADATA
boobs-0.6.9.dist-info/WHEEL
boobs-0.6.9.dist-info/RECORD
