Metadata-Version: 2.1
Name: boobs
Version: 0.6.9
Summary: Asynchronous feature-rich framework for building Telegram bots
Home-page: https://github.com/wondergram-org/boobs/
License: MIT
Requires-Python: >=3.10,<4.0
Classifier: License :: OSI Approved :: MIT License
Classifier: Programming Language :: Python :: 3
Classifier: Programming Language :: Python :: 3.10
Classifier: Programming Language :: Python :: 3.11
Requires-Dist: aiohttp (>=3.8.5,<4.0.0)
Requires-Dist: certifi (>=2023.7.22,<2024.0.0)
Requires-Dist: choicelib (>=0.1.5,<0.2.0)
Requires-Dist: msgspec (>=0.18.0,<0.19.0)
Requires-Dist: structlog (>=23.1.0,<24.0.0)
